example/__init__.py
example/local.py
example/settings.py
example/urls.py
example/wsgi.py
logingovpl/__init__.py
logingovpl/apps.py
logingovpl/conf.py
logingovpl/forms.py
logingovpl/mixins.py
logingovpl/models.py
logingovpl/objects.py
logingovpl/services.py
logingovpl/statuses.py
logingovpl/urls.py
logingovpl/utils.py
logingovpl/views.py
logingovpl/templates/ArtifactResolve.xml
logingovpl/templates/AuthnRequest.xml
logingovpl/templates/Envelop.html
django_logingovpl-0.0.4.dist-info/LICENSE
django_logingovpl-0.0.4.dist-info/METADATA
django_logingovpl-0.0.4.dist-info/WHEEL
django_logingovpl-0.0.4.dist-info/top_level.txt
django_logingovpl-0.0.4.dist-info/RECORD
